{"cameraMode":{"drawMode":0,"name":"Shaded","section":"Shading Mode"},"sceneLighting":true,"audioPlay":false,"sceneViewState":{"m_AlwaysRefresh":false,"showFog":true,"showSkybox":true,"showFlares":true,"showImageEffects":true,"showParticleSystems":true,"showVisualEffectGraphs":true,"m_FxEnabled":true},"in2DMode":false,"pivot":{"x":-0.4116244316101074,"y":-3.8557543754577638,"z":-42.0249137878418},"rotation":{"x":-0.3320944011211395,"y":0.5481644868850708,"z":-0.25094202160835268,"w":-0.7254365682601929},"size":22.97041130065918,"orthographic":false}